README.md
setup.py
mvvmQt/Attributes.py
mvvmQt/Elements.py
mvvmQt/Events.py
mvvmQt/Observable.py
mvvmQt/Parser.py
mvvmQt/__init__.py
mvvmQt/alignConfig.py
mvvmQt/attrConfig.py
mvvmQt/attrFuncs.py
mvvmQt/attrTypes.py
mvvmQt/rewriteContorls.py
mvvmQt.egg-info/PKG-INFO
mvvmQt.egg-info/SOURCES.txt
mvvmQt.egg-info/dependency_links.txt
mvvmQt.egg-info/requires.txt
mvvmQt.egg-info/top_level.txt