Metadata-Version: 2.1
Name: mvvmQt
Version: 0.35.5
Summary: write qt like html
Home-page: https://gitee.com/zhiyang/py-qt-dom
Author: Norman
Author-email: 332535694@qq.com
License: UNKNOWN
Platform: UNKNOWN
Requires-Python: >=3.8.10
